distributions/Binomialdistribution.py
distributions/Gaussiandistribution.py
distributions/Generaldistribution.py
distributions/__init__.py
Dollypee_Distributions-0.1.dist-info/METADATA
Dollypee_Distributions-0.1.dist-info/WHEEL
Dollypee_Distributions-0.1.dist-info/top_level.txt
Dollypee_Distributions-0.1.dist-info/RECORD
