Metadata-Version: 2.1
Name: Dollypee_Distributions
Version: 0.1
Summary: This is the homepage of our project   Dollypee probability
Home-page: UNKNOWN
License: UNKNOWN
Platform: UNKNOWN
